flake8_django_migrations/__init__.py
flake8_django_migrations/plugin.py
flake8_django_migrations/checkers/__init__.py
flake8_django_migrations/checkers/base.py
flake8_django_migrations/checkers/issue.py
flake8_django_migrations/checkers/remove_field.py
flake8_django_migrations-1.2.0.dist-info/METADATA
flake8_django_migrations-1.2.0.dist-info/WHEEL
flake8_django_migrations-1.2.0.dist-info/entry_points.txt
flake8_django_migrations-1.2.0.dist-info/top_level.txt
flake8_django_migrations-1.2.0.dist-info/RECORD
