Metadata-Version: 2.4
Name: flake8-django-migrations
Version: 1.2.0
Summary: Flake8 plugin to lint for backwards incompatible database migrations
Author-email: Bruno Alla <bruno.alla@festicket.com>
License-Expression: MIT
Project-URL: repository, https://github.com/browniebroke/flake8-django-migrations
Keywords: django,flake8,lint,migrations
Classifier: Development Status :: 1 - Planning
Classifier: Environment :: Console
Classifier: Framework :: Flake8
Classifier: Intended Audience :: Developers
Classifier: Natural Language :: English
Classifier: Operating System :: OS Independent
Classifier: Programming Language :: Python :: 3 :: Only
Classifier: Programming Language :: Python :: 3.10
Classifier: Programming Language :: Python :: 3.11
Classifier: Programming Language :: Python :: 3.12
Classifier: Programming Language :: Python :: 3.13
Classifier: Programming Language :: Python :: 3.14
Classifier: Topic :: Software Development :: Quality Assurance
Requires-Python: >=3.10
Requires-Dist: astor>=0.1
Requires-Dist: flake8>=3.7
Requires-Dist: importlib-metadata>=0.9; python_version < "3.8"
